tox_cmake
