Metadata-Version: 1.1
Name: tox-cmake
Version: 0.1.1
Summary: Build CMake projects using Tox
Home-page: UNKNOWN
Author: Andre Caron
Author-email: andre.l.caron@gmail.com
License: http://opensource.org/licenses/MIT
Keywords: tox cmake
Platform: win32
Classifier: Development Status :: 3 - Alpha
Classifier: Intended Audience :: Developers
Classifier: License :: OSI Approved :: MIT License
Classifier: Operating System :: Microsoft :: Windows
Classifier: Programming Language :: C++
Classifier: Programming Language :: Python
Classifier: Programming Language :: Python :: 2
Classifier: Programming Language :: Python :: 3
Classifier: Topic :: Software Development :: Testing
